fasva_osmserver-0.1.6.data/data/share/osmserver.cfg
fasva_osmserver-0.1.6.data/data/share/osmserver.service
osmserver/__init__.py
osmserver/handler.py
osmserver/osm.py
osmserver/server.py
fasva_osmserver-0.1.6.dist-info/LICENSE
fasva_osmserver-0.1.6.dist-info/METADATA
fasva_osmserver-0.1.6.dist-info/WHEEL
fasva_osmserver-0.1.6.dist-info/entry_points.txt
fasva_osmserver-0.1.6.dist-info/top_level.txt
fasva_osmserver-0.1.6.dist-info/RECORD
