Metadata-Version: 2.1
Name: fasva-osmserver
Version: 0.1.6
Summary: Server to query the OpenStreetMap service.
Home-page: UNKNOWN
Author: Lars Klitzke
Author-email: lars.klitzke@hs-emden-leer.de
License: UNKNOWN
Platform: UNKNOWN
Classifier: Operating System :: OS Independent
Classifier: Programming Language :: Python :: 3.5
Classifier: Programming Language :: Python :: 3.6
Classifier: Programming Language :: Python :: 3.7
Classifier: License :: OSI Approved :: GNU General Public License v3 or later (GPLv3+)
Classifier: Topic :: Software Development :: Libraries :: Application Frameworks
Classifier: Natural Language :: English
Classifier: Intended Audience :: Developers
Requires-Dist: aiohttp
Requires-Dist: pymodconf
